README.rst
setup.py
papir/__init__.py
papir/papir.py
papir.egg-info/PKG-INFO
papir.egg-info/SOURCES.txt
papir.egg-info/dependency_links.txt
papir.egg-info/entry_points.txt
papir.egg-info/top_level.txt