Metadata-Version: 1.0
Name: papir
Version: 0.3.0
Summary: Make http requests to json apis
Home-page: https://github.com/pdrb/papir
Author: Pedro Buteri Gonring
Author-email: pedro@bigode.net
License: MIT
Keywords: http api json requests
Platform: UNKNOWN
